django_tctip/__init__.py
django_tctip/admin.py
django_tctip/apps.py
django_tctip/models.py
django_tctip/migrations/0001_initial.py
django_tctip/migrations/__init__.py
django_tctip/static/tctip/css/tctip.min.css
django_tctip/static/tctip/js/tctip.min.js
django_tctip/templates/tctip/tips.html
django_tctip/templatetags/__init__.py
django_tctip/templatetags/tctip_tags.py
django_tctip-1.4.7.dist-info/LICENSE
django_tctip-1.4.7.dist-info/METADATA
django_tctip-1.4.7.dist-info/WHEEL
django_tctip-1.4.7.dist-info/top_level.txt
django_tctip-1.4.7.dist-info/RECORD
